{".class":"MypyFile","_fullname":"npc_sessions.utils.videos","future_import_flags":["annotations"],"is_partial_stub_package":false,"is_stub":false,"names":{".class":"SymbolTable","FACEMAP_CAMERA_NAMES":{".class":"SymbolTableNode","kind":"Gdef","node":{".class":"Var","flags":["is_ready","has_explicit_value"],"fullname":"npc_sessions.utils.videos.FACEMAP_CAMERA_NAMES","name":"FACEMAP_CAMERA_NAMES","type":{".class":"Instance","args":[{".class":"TypeAliasType","args":[],"type_ref":"npc_mvr.mvr.CameraName"}],"extra_attrs":null,"type_ref":"builtins.tuple"}}},"LP_CAMERA_NAMES":{".class":"SymbolTableNode","kind":"Gdef","node":{".class":"Var","flags":["is_inferred","has_explicit_value"],"fullname":"npc_sessions.utils.videos.LP_CAMERA_NAMES","name":"LP_CAMERA_NAMES","type":{".class":"TupleType","implicit":false,"items":["builtins.str","builtins.str"],"partial_fallback":{".class":"Instance","args":[{".class":"AnyType","missing_import_name":null,"source_any":null,"type_of_any":6}],"extra_attrs":null,"type_ref":"builtins.tuple"}}}},"LP_MAPPING":{".class":"SymbolTableNode","kind":"Gdef","node":{".class":"Var","flags":["is_inferred","has_explicit_value"],"fullname":"npc_sessions.utils.videos.LP_MAPPING","name":"LP_MAPPING","type":{".class":"Instance","args":["builtins.str","builtins.str"],"extra_attrs":null,"type_ref":"builtins.dict"}}},"LP_RESULT_DESCRIPTIONS":{".class":"SymbolTableNode","kind":"Gdef","node":{".class":"Var","flags":["is_inferred","has_explicit_value"],"fullname":"npc_sessions.utils.videos.LP_RESULT_DESCRIPTIONS","name":"LP_RESULT_DESCRIPTIONS","type":{".class":"Instance","args":["builtins.str","builtins.str"],"extra_attrs":null,"type_ref":"builtins.dict"}}},"LP_RESULT_TYPES":{".class":"SymbolTableNode","kind":"Gdef","node":{".class":"Var","flags":["is_inferred","has_explicit_value"],"fullname":"npc_sessions.utils.videos.LP_RESULT_TYPES","name":"LP_RESULT_TYPES","type":{".class":"TupleType","implicit":false,"items":["builtins.str","builtins.str","builtins.str"],"partial_fallback":{".class":"Instance","args":[{".class":"AnyType","missing_import_name":null,"source_any":null,"type_of_any":6}],"extra_attrs":null,"type_ref":"builtins.tuple"}}}},"LP_VIDEO_FEATURES_MAPPING":{".class":"SymbolTableNode","kind":"Gdef","node":{".class":"Var","flags":["is_inferred","has_explicit_value"],"fullname":"npc_sessions.utils.videos.LP_VIDEO_FEATURES_MAPPING","name":"LP_VIDEO_FEATURES_MAPPING","type":{".class":"Instance","args":["builtins.str",{".class":"Instance","args":["builtins.str"],"extra_attrs":null,"type_ref":"builtins.tuple"}],"extra_attrs":null,"type_ref":"builtins.dict"}}},"Literal":{".class":"SymbolTableNode","cross_ref":"typing.Literal","kind":"Gdef"},"MODEL_FUNCTION_MAPPING":{".class":"SymbolTableNode","kind":"Gdef","node":{".class":"Var","flags":["is_inferred","has_explicit_value"],"fullname":"npc_sessions.utils.videos.MODEL_FUNCTION_MAPPING","name":"MODEL_FUNCTION_MAPPING","type":{".class":"Instance","args":["builtins.str",{".class":"Instance","args":[{".class":"Instance","args":["upath.core.UPath"],"extra_attrs":null,"type_ref":"builtins.tuple"}],"extra_attrs":null,"type_ref":"functools._lru_cache_wrapper"}],"extra_attrs":null,"type_ref":"builtins.dict"}}},"__annotations__":{".class":"SymbolTableNode","kind":"Gdef","node":{".class":"Var","flags":["is_ready"],"fullname":"npc_sessions.utils.videos.__annotations__","name":"__annotations__","type":{".class":"Instance","args":["builtins.str",{".class":"AnyType","missing_import_name":null,"source_any":null,"type_of_any":6}],"extra_attrs":null,"type_ref":"builtins.dict"}}},"__doc__":{".class":"SymbolTableNode","kind":"Gdef","node":{".class":"Var","flags":["is_ready"],"fullname":"npc_sessions.utils.videos.__doc__","name":"__doc__","type":"builtins.str"}},"__file__":{".class":"SymbolTableNode","kind":"Gdef","node":{".class":"Var","flags":["is_ready"],"fullname":"npc_sessions.utils.videos.__file__","name":"__file__","type":"builtins.str"}},"__name__":{".class":"SymbolTableNode","kind":"Gdef","node":{".class":"Var","flags":["is_ready"],"fullname":"npc_sessions.utils.videos.__name__","name":"__name__","type":"builtins.str"}},"__package__":{".class":"SymbolTableNode","kind":"Gdef","node":{".class":"Var","flags":["is_ready"],"fullname":"npc_sessions.utils.videos.__package__","name":"__package__","type":"builtins.str"}},"__spec__":{".class":"SymbolTableNode","kind":"Gdef","node":{".class":"Var","flags":["is_ready"],"fullname":"npc_sessions.utils.videos.__spec__","name":"__spec__","type":"importlib.machinery.ModuleSpec"}},"_get_LPFaceParts_predictions_dataframe":{".class":"SymbolTableNode","kind":"Gdef","node":{".class":"FuncDef","abstract_status":0,"arg_kinds":[0],"arg_names":["df_predictions"],"dataclass_transform_spec":null,"flags":[],"fullname":"npc_sessions.utils.videos._get_LPFaceParts_predictions_dataframe","name":"_get_LPFaceParts_predictions_dataframe","type":{".class":"CallableType","arg_kinds":[0],"arg_names":["df_predictions"],"arg_types":[{".class":"AnyType","missing_import_name":"npc_sessions.utils.videos.pd","source_any":null,"type_of_any":3}],"bound_args":[],"def_extras":{"first_arg":null},"fallback":"builtins.function","from_concatenate":false,"implicit":false,"imprecise_arg_kinds":false,"is_ellipsis_args":false,"name":"_get_LPFaceParts_predictions_dataframe","ret_type":{".class":"AnyType","missing_import_name":"npc_sessions.utils.videos.pd","source_any":null,"type_of_any":3},"type_guard":null,"type_is":null,"unpack_kwargs":false,"variables":[]}}},"annotations":{".class":"SymbolTableNode","cross_ref":"__future__.annotations","kind":"Gdef"},"doctest":{".class":"SymbolTableNode","cross_ref":"doctest","kind":"Gdef"},"get_LPFaceParts_result_dataframe":{".class":"SymbolTableNode","kind":"Gdef","node":{".class":"FuncDef","abstract_status":0,"arg_kinds":[0,0,0],"arg_names":["session","camera","result_name"],"dataclass_transform_spec":null,"flags":[],"fullname":"npc_sessions.utils.videos.get_LPFaceParts_result_dataframe","name":"get_LPFaceParts_result_dataframe","type":{".class":"CallableType","arg_kinds":[0,0,0],"arg_names":["session","camera","result_name"],"arg_types":["builtins.str","builtins.str","builtins.str"],"bound_args":[],"def_extras":{"first_arg":null},"fallback":"builtins.function","from_concatenate":false,"implicit":false,"imprecise_arg_kinds":false,"is_ellipsis_args":false,"name":"get_LPFaceParts_result_dataframe","ret_type":{".class":"AnyType","missing_import_name":"npc_sessions.utils.videos.pd","source_any":null,"type_of_any":3},"type_guard":null,"type_is":null,"unpack_kwargs":false,"variables":[]}}},"get_dlc_session_model_dataframe_from_h5":{".class":"SymbolTableNode","kind":"Gdef","node":{".class":"FuncDef","abstract_status":0,"arg_kinds":[0,0],"arg_names":["session","model_name"],"dataclass_transform_spec":null,"flags":[],"fullname":"npc_sessions.utils.videos.get_dlc_session_model_dataframe_from_h5","name":"get_dlc_session_model_dataframe_from_h5","type":{".class":"CallableType","arg_kinds":[0,0],"arg_names":["session","model_name"],"arg_types":["builtins.str","builtins.str"],"bound_args":[],"def_extras":{"first_arg":null},"fallback":"builtins.function","from_concatenate":false,"implicit":false,"imprecise_arg_kinds":false,"is_ellipsis_args":false,"name":"get_dlc_session_model_dataframe_from_h5","ret_type":{".class":"AnyType","missing_import_name":"npc_sessions.utils.videos.pd","source_any":null,"type_of_any":3},"type_guard":null,"type_is":null,"unpack_kwargs":false,"variables":[]}}},"get_dlc_session_paf_graph":{".class":"SymbolTableNode","kind":"Gdef","node":{".class":"FuncDef","abstract_status":0,"arg_kinds":[0,0],"arg_names":["session","model_name"],"dataclass_transform_spec":null,"flags":[],"fullname":"npc_sessions.utils.videos.get_dlc_session_paf_graph","name":"get_dlc_session_paf_graph","type":{".class":"CallableType","arg_kinds":[0,0],"arg_names":["session","model_name"],"arg_types":["builtins.str","builtins.str"],"bound_args":[],"def_extras":{"first_arg":null},"fallback":"builtins.function","from_concatenate":false,"implicit":false,"imprecise_arg_kinds":false,"is_ellipsis_args":false,"name":"get_dlc_session_paf_graph","ret_type":{".class":"Instance","args":[{".class":"AnyType","missing_import_name":null,"source_any":null,"type_of_any":4}],"extra_attrs":null,"type_ref":"builtins.list"},"type_guard":null,"type_is":null,"unpack_kwargs":false,"variables":[]}}},"get_ellipse_session_dataframe_from_h5":{".class":"SymbolTableNode","kind":"Gdef","node":{".class":"FuncDef","abstract_status":0,"arg_kinds":[0],"arg_names":["session"],"dataclass_transform_spec":null,"flags":[],"fullname":"npc_sessions.utils.videos.get_ellipse_session_dataframe_from_h5","name":"get_ellipse_session_dataframe_from_h5","type":{".class":"CallableType","arg_kinds":[0],"arg_names":["session"],"arg_types":["builtins.str"],"bound_args":[],"def_extras":{"first_arg":null},"fallback":"builtins.function","from_concatenate":false,"implicit":false,"imprecise_arg_kinds":false,"is_ellipsis_args":false,"name":"get_ellipse_session_dataframe_from_h5","ret_type":{".class":"AnyType","missing_import_name":"npc_sessions.utils.videos.pd","source_any":null,"type_of_any":3},"type_guard":null,"type_is":null,"unpack_kwargs":false,"variables":[]}}},"get_facemap_output_from_s3":{".class":"SymbolTableNode","kind":"Gdef","node":{".class":"FuncDef","abstract_status":0,"arg_kinds":[0,0,0],"arg_names":["session","camera_name","array_name"],"dataclass_transform_spec":null,"flags":[],"fullname":"npc_sessions.utils.videos.get_facemap_output_from_s3","name":"get_facemap_output_from_s3","type":{".class":"CallableType","arg_kinds":[0,0,0],"arg_names":["session","camera_name","array_name"],"arg_types":["builtins.str",{".class":"TypeAliasType","args":[],"type_ref":"npc_mvr.mvr.CameraName"},{".class":"UnionType","items":[{".class":"LiteralType","fallback":"builtins.str","value":"motSVD"},{".class":"LiteralType","fallback":"builtins.str","value":"proc"}],"uses_pep604_syntax":false}],"bound_args":[],"def_extras":{"first_arg":null},"fallback":"builtins.function","from_concatenate":false,"implicit":false,"imprecise_arg_kinds":false,"is_ellipsis_args":false,"name":"get_facemap_output_from_s3","ret_type":{".class":"AnyType","missing_import_name":"npc_sessions.utils.videos.zarr","source_any":null,"type_of_any":3},"type_guard":null,"type_is":null,"unpack_kwargs":false,"variables":[]}}},"get_pose_series_from_dataframe":{".class":"SymbolTableNode","kind":"Gdef","node":{".class":"FuncDef","abstract_status":0,"arg_kinds":[0,0,0],"arg_names":["session","df","video_timestamps"],"dataclass_transform_spec":null,"flags":[],"fullname":"npc_sessions.utils.videos.get_pose_series_from_dataframe","name":"get_pose_series_from_dataframe","type":{".class":"CallableType","arg_kinds":[0,0,0],"arg_names":["session","df","video_timestamps"],"arg_types":["builtins.str",{".class":"AnyType","missing_import_name":"npc_sessions.utils.videos.pd","source_any":null,"type_of_any":3},{".class":"TypeAliasType","args":[{".class":"TypeAliasType","args":[],"type_ref":"numpy.float64"}],"type_ref":"numpy._typing._array_like.NDArray"}],"bound_args":[],"def_extras":{"first_arg":null},"fallback":"builtins.function","from_concatenate":false,"implicit":false,"imprecise_arg_kinds":false,"is_ellipsis_args":false,"name":"get_pose_series_from_dataframe","ret_type":{".class":"Instance","args":[{".class":"AnyType","missing_import_name":"npc_sessions.utils.videos.ndx_pose","source_any":null,"type_of_any":3}],"extra_attrs":null,"type_ref":"builtins.list"},"type_guard":null,"type_is":null,"unpack_kwargs":false,"variables":[]}}},"h5_to_dataframe":{".class":"SymbolTableNode","kind":"Gdef","node":{".class":"FuncDef","abstract_status":0,"arg_kinds":[0,1],"arg_names":["h5_path","key_name"],"dataclass_transform_spec":null,"flags":[],"fullname":"npc_sessions.utils.videos.h5_to_dataframe","name":"h5_to_dataframe","type":{".class":"CallableType","arg_kinds":[0,1],"arg_names":["h5_path","key_name"],"arg_types":["upath.core.UPath",{".class":"UnionType","items":["builtins.str",{".class":"NoneType"}],"uses_pep604_syntax":true}],"bound_args":[],"def_extras":{"first_arg":null},"fallback":"builtins.function","from_concatenate":false,"implicit":false,"imprecise_arg_kinds":false,"is_ellipsis_args":false,"name":"h5_to_dataframe","ret_type":{".class":"AnyType","missing_import_name":"npc_sessions.utils.videos.pd","source_any":null,"type_of_any":3},"type_guard":null,"type_is":null,"unpack_kwargs":false,"variables":[]}}},"ndx_pose":{".class":"SymbolTableNode","kind":"Gdef","node":{".class":"Var","flags":["is_suppressed_import","is_ready","is_inferred"],"fullname":"npc_sessions.utils.videos.ndx_pose","name":"ndx_pose","type":{".class":"AnyType","missing_import_name":"npc_sessions.utils.videos.ndx_pose","source_any":null,"type_of_any":3}}},"np":{".class":"SymbolTableNode","cross_ref":"numpy","kind":"Gdef"},"npc_lims":{".class":"SymbolTableNode","cross_ref":"npc_lims","kind":"Gdef"},"npc_mvr":{".class":"SymbolTableNode","cross_ref":"npc_mvr","kind":"Gdef"},"npt":{".class":"SymbolTableNode","cross_ref":"numpy.typing","kind":"Gdef"},"pd":{".class":"SymbolTableNode","kind":"Gdef","node":{".class":"Var","flags":["is_suppressed_import","is_ready","is_inferred"],"fullname":"npc_sessions.utils.videos.pd","name":"pd","type":{".class":"AnyType","missing_import_name":"npc_sessions.utils.videos.pd","source_any":null,"type_of_any":3}}},"tempfile":{".class":"SymbolTableNode","cross_ref":"tempfile","kind":"Gdef"},"upath":{".class":"SymbolTableNode","cross_ref":"upath","kind":"Gdef"},"zarr":{".class":"SymbolTableNode","kind":"Gdef","node":{".class":"Var","flags":["is_suppressed_import","is_ready","is_inferred"],"fullname":"npc_sessions.utils.videos.zarr","name":"zarr","type":{".class":"AnyType","missing_import_name":"npc_sessions.utils.videos.zarr","source_any":null,"type_of_any":3}}}},"path":"c:\\Users\\ben.hardcastle\\github\\np_workflows\\.venv\\Lib\\site-packages\\npc_sessions\\utils\\videos.py"}