{"data_mtime":1731712094,"dep_lines":[7,8,19,20,21,31,1,3,4,5,7,1,1,1,1,1,1,1,1,1,1,1,1,1,1,1,1,1,1,1,1,1,1,1,1,1,1,1,1,1,1,1,1,1,1,1,1,1,1,1,1,1,1,1,1,1,1,1,1,1,1,1,1,1,1,1,1,1,1,1,1,1,1,1,1,1,27,28,26],"dep_prios":[10,5,5,5,5,25,5,5,5,5,20,5,20,20,20,20,20,20,20,20,20,20,20,20,20,20,20,20,20,20,20,20,20,20,20,20,20,20,20,20,20,20,20,20,20,20,20,20,20,20,20,20,20,20,20,20,20,20,20,20,20,20,20,20,20,20,20,20,30,30,30,30,30,30,30,30,25,25,25],"dependencies":["polars.functions","polars.datatypes","polars.dependencies","polars.exceptions","polars.selectors","polars.type_aliases","__future__","io","pathlib","typing","polars","builtins","collections","npc_lims.status.tracked_sessions","npc_session.parsing","npc_mvr","pprint","pickle","aind_session","time","numpy","json","operator","sqlite3","uuid","itertools","contextlib","npc_lims.paths.s3","npc_io","upath","npc_lims","rich","datetime","inspect","os","npc_sync","npc_lims.status.behavior_sessions","dotenv","npc_lims.exceptions","traceback","warnings","dataclasses","zoneinfo","sys","packaging","subprocess","npc_session","types","tempfile","importlib","doctest","functools","npc_lims.metadata.codeocean_utils","matplotlib.pyplot","pyexpat.errors","copy","re","requests","cv2","logging","html","yaml","matplotlib","shutil","string","numpy.typing","npc_stim","pyexpat.model","abc","importlib.machinery","polars.dataframe","polars.dataframe.frame","polars.datatypes.classes","polars.datatypes.constants","polars.expr","polars.expr.expr"],"hash":"df34196ae71c6a9baa42ab72bef1fcd58400e8bc9e5b06354697a15ec770867a","id":"polars.io.spreadsheet._write_utils","ignore_all":true,"interface_hash":"a15e66d029888d973e37d4621c52eab14a7ffe4f8fe8437b12f7462f20250120","mtime":1715708410,"options":{"allow_redefinition":false,"allow_untyped_globals":false,"always_false":[],"always_true":[],"bazel":false,"check_untyped_defs":false,"disable_bytearray_promotion":false,"disable_error_code":[],"disable_memoryview_promotion":false,"disabled_error_codes":[],"disallow_any_decorated":false,"disallow_any_explicit":false,"disallow_any_expr":false,"disallow_any_generics":false,"disallow_any_unimported":false,"disallow_incomplete_defs":false,"disallow_subclassing_any":false,"disallow_untyped_calls":false,"disallow_untyped_decorators":false,"disallow_untyped_defs":false,"enable_error_code":[],"enabled_error_codes":[],"extra_checks":false,"follow_imports":"normal","follow_imports_for_stubs":false,"ignore_errors":false,"ignore_missing_imports":false,"implicit_optional":false,"implicit_reexport":true,"local_partial_types":false,"mypyc":false,"old_type_inference":false,"platform":"win32","plugins":[],"strict_concatenate":false,"strict_equality":false,"strict_optional":true,"warn_no_return":true,"warn_return_any":false,"warn_unreachable":false,"warn_unused_ignores":false},"path":"c:\\Users\\ben.hardcastle\\github\\np_workflows\\.venv\\Lib\\site-packages\\polars\\io\\spreadsheet\\_write_utils.py","plugin_data":null,"size":20303,"suppressed":["xlsxwriter.format","xlsxwriter.worksheet","xlsxwriter"],"version_id":"1.11.2"}